ricciardi/__init__.py
ricciardi/ricciardi.py
ricciardi-0.1.6.dist-info/LICENSE
ricciardi-0.1.6.dist-info/METADATA
ricciardi-0.1.6.dist-info/WHEEL
ricciardi-0.1.6.dist-info/top_level.txt
ricciardi-0.1.6.dist-info/RECORD
