Metadata-Version: 2.2
Name: ricciardi
Version: 0.1.6
Summary: PyTorch implementation of the Ricciardi transfer function.
Author: Ho Yin Chau
License: MIT License
Project-URL: repository, https://github.com/hchau630/ricciardi
Classifier: License :: OSI Approved :: MIT License
Classifier: Natural Language :: English
Classifier: Operating System :: OS Independent
Classifier: Programming Language :: Python :: 3.9
Classifier: Programming Language :: Python :: 3.10
Classifier: Programming Language :: Python :: 3.11
Classifier: Programming Language :: Python :: 3.12
Requires-Python: >=3.9
License-File: LICENSE
Requires-Dist: scipy
Requires-Dist: torch
